{"Objnum":5,"objects":[{"name":"andGate","posX":453,"posY":157},{"name":"andGate","posX":445,"posY":467},{"name":"notGate","posX":241,"posY":136},{"name":"notGate","posX":256,"posY":487},{"name":"orGate","posX":764,"posY":332}],"NodeNum":3,"nodes":[{"type":"input","posX":56,"posY":137},{"type":"input","posX":80,"posY":478},{"type":"output","posX":1152,"posY":339}],"WireNum":9,"wires":[{"inputNodeIdx":0,"outputNodeIdx":-1,"inputObjIdx":-1,"outputObjIdx":2,"inputIndex":0,"outputIndex":-1},{"inputNodeIdx":-1,"outputNodeIdx":-1,"inputObjIdx":2,"outputObjIdx":0,"inputIndex":0,"outputIndex":0},{"inputNodeIdx":1,"outputNodeIdx":-1,"inputObjIdx":-1,"outputObjIdx":3,"inputIndex":0,"outputIndex":-1},{"inputNodeIdx":-1,"outputNodeIdx":-1,"inputObjIdx":3,"outputObjIdx":1,"inputIndex":1,"outputIndex":0},{"inputNodeIdx":0,"outputNodeIdx":-1,"inputObjIdx":-1,"outputObjIdx":1,"inputIndex":0,"outputIndex":-1},{"inputNodeIdx":1,"outputNodeIdx":-1,"inputObjIdx":-1,"outputObjIdx":0,"inputIndex":1,"outputIndex":-1},{"inputNodeIdx":-1,"outputNodeIdx":-1,"inputObjIdx":0,"outputObjIdx":4,"inputIndex":0,"outputIndex":0},{"inputNodeIdx":-1,"outputNodeIdx":-1,"inputObjIdx":1,"outputObjIdx":4,"inputIndex":1,"outputIndex":0},{"inputNodeIdx":-1,"outputNodeIdx":2,"inputObjIdx":4,"outputObjIdx":-1,"inputIndex":-1,"outputIndex":0}]}